odoo8_addon_project_task_department-8.0.1.0.0-py2.7-nspkg.pth
odoo8_addon_project_task_department-8.0.1.0.0.dist-info/top_level.txt
odoo8_addon_project_task_department-8.0.1.0.0.dist-info/WHEEL
odoo8_addon_project_task_department-8.0.1.0.0.dist-info/RECORD
odoo8_addon_project_task_department-8.0.1.0.0.dist-info/metadata.json
odoo8_addon_project_task_department-8.0.1.0.0.dist-info/DESCRIPTION.rst
odoo8_addon_project_task_department-8.0.1.0.0.dist-info/METADATA
odoo8_addon_project_task_department-8.0.1.0.0.dist-info/namespace_packages.txt
odoo_addons/project_task_department/project_view.xml
odoo_addons/project_task_department/__openerp__.py
odoo_addons/project_task_department/project_task.py
odoo_addons/project_task_department/__init__.py
odoo_addons/project_task_department/LICENSE
