Metadata-Version: 2.0
Name: odoo8-addon-project-task-department
Version: 8.0.1.0.0
Summary: Project Task specific Department
Home-page: https://github.com/OCA/project-service
Author: UNKNOWN
Author-email: UNKNOWN
License: AGPL-3
Platform: UNKNOWN
Requires-Dist: odoo (<9.0a,>=8.0a)
Requires-Dist: odoo8-addon-project-department
Classifier: Programming Language :: Python :: 2.7
Classifier: Framework :: Odoo
Classifier: License :: OSI Approved :: GNU Affero General Public License v3
